bioversions/__init__.py
bioversions/__main__.py
bioversions/charts.py
bioversions/cli.py
bioversions/py.typed
bioversions/resources/__init__.py
bioversions/resources/update.py
bioversions/resources/versions.json
bioversions/slack_client.py
bioversions/sources/__init__.py
bioversions/sources/antibodyregistry.py
bioversions/sources/bigg.py
bioversions/sources/biogrid.py
bioversions/sources/ccle.py
bioversions/sources/cellosaurus.py
bioversions/sources/chebi.py
bioversions/sources/chembl.py
bioversions/sources/chemidplus.py
bioversions/sources/civic.py
bioversions/sources/complexportal.py
bioversions/sources/daily.py
bioversions/sources/depmap.py
bioversions/sources/dgi.py
bioversions/sources/disgenet.py
bioversions/sources/drugbank.py
bioversions/sources/drugcentral.py
bioversions/sources/ensembl.py
bioversions/sources/expasy.py
bioversions/sources/flybase.py
bioversions/sources/gtdb.py
bioversions/sources/guidetopharmacology.py
bioversions/sources/hgnc.py
bioversions/sources/homologene.py
bioversions/sources/icd10.py
bioversions/sources/icd11.py
bioversions/sources/icf.py
bioversions/sources/intact.py
bioversions/sources/interpro.py
bioversions/sources/itis.py
bioversions/sources/kegg.py
bioversions/sources/loinc.py
bioversions/sources/mesh.py
bioversions/sources/mgi.py
bioversions/sources/mirbase.py
bioversions/sources/moalmanac.py
bioversions/sources/msigdb.py
bioversions/sources/ncit.py
bioversions/sources/npass.py
bioversions/sources/obo.py
bioversions/sources/ols.py
bioversions/sources/omim.py
bioversions/sources/oncotree.py
bioversions/sources/pathbank.py
bioversions/sources/pathwaycommons.py
bioversions/sources/pfam.py
bioversions/sources/pombase.py
bioversions/sources/pr.py
bioversions/sources/pubchem.py
bioversions/sources/reactome.py
bioversions/sources/rfam.py
bioversions/sources/rgd.py
bioversions/sources/rhea.py
bioversions/sources/ror.py
bioversions/sources/rxnorm.py
bioversions/sources/sgd.py
bioversions/sources/signor.py
bioversions/sources/silva.py
bioversions-0.8.252.dist-info/licenses/LICENSE
bioversions-0.8.252.dist-info/WHEEL
bioversions-0.8.252.dist-info/entry_points.txt
bioversions-0.8.252.dist-info/METADATA
bioversions-0.8.252.dist-info/RECORD
