Metadata-Version: 2.4
Name: bioversions
Version: 0.8.252
Summary: Get the current version for biological databases
Keywords: snekpack,cookiecutter,databases,biological databases,biomedical databases
Author: Charles Tapley Hoyt
Author-email: Charles Tapley Hoyt <cthoyt@gmail.com>
License-File: LICENSE
Classifier: Development Status :: 4 - Beta
Classifier: Environment :: Console
Classifier: Intended Audience :: Developers
Classifier: License :: OSI Approved :: MIT License
Classifier: Operating System :: OS Independent
Classifier: Framework :: Pytest
Classifier: Framework :: tox
Classifier: Framework :: Sphinx
Classifier: Natural Language :: English
Classifier: Programming Language :: Python
Classifier: Programming Language :: Python :: 3.10
Classifier: Programming Language :: Python :: 3.11
Classifier: Programming Language :: Python :: 3.12
Classifier: Programming Language :: Python :: 3.13
Classifier: Programming Language :: Python :: 3 :: Only
Classifier: Typing :: Typed
Requires-Dist: requests
Requires-Dist: beautifulsoup4
Requires-Dist: cachier>=2.2.1
Requires-Dist: pystow[bs4]>=0.7.8
Requires-Dist: click
Requires-Dist: click-default-group
Requires-Dist: dataclasses-json
Requires-Dist: tabulate
Requires-Dist: more-click
Requires-Dist: pyyaml
Requires-Dist: tqdm
Requires-Dist: bioregistry[align]>=0.11.35
Requires-Dist: lxml
Requires-Dist: pydantic>=2.0
Requires-Dist: psycopg2-binary
Requires-Dist: python-dateutil
Requires-Dist: class-resolver>=0.7.1
Requires-Dist: ror-downloader>=0.0.4
Requires-Dist: matplotlib ; extra == 'charts'
Requires-Dist: seaborn ; extra == 'charts'
Requires-Dist: slack-sdk ; extra == 'slack'
Requires-Dist: tweepy ; extra == 'twitter'
Requires-Dist: flask ; extra == 'web'
Requires-Dist: bootstrap-flask ; extra == 'web'
Maintainer: Charles Tapley Hoyt
Maintainer-email: Charles Tapley Hoyt <cthoyt@gmail.com>
Requires-Python: >=3.10
Project-URL: Bug Tracker, https://github.com/biopragmatics/bioversions/issues
Project-URL: Homepage, https://github.com/biopragmatics/bioversions
Project-URL: Repository, https://github.com/biopragmatics/bioversions.git
Project-URL: Documentation, https://bioversions.readthedocs.io
Project-URL: Funding, https://github.com/sponsors/cthoyt
Provides-Extra: charts
Provides-Extra: slack
Provides-Extra: twitter
Provides-Extra: web
